<?xml version="1.0" encoding="UTF-8"?>
<SAR>
  <ReportID>INV2024-017-001</ReportID>
  <ReportingInstitution>Credobank Austria</ReportingInstitution>
  <Subject>
    <Name>Hans Gruber</Name>
    <Account>AT141100000000000004789012</Account>
  </Subject>
  <Transaction>
    <Date>2023-10-01</Date>
    <Amount>12000</Amount>
    <Currency>EUR</Currency>
    <DestinationAccount>LT12100001110123451</DestinationAccount>
    <DestinationName>Altcoin Global Ltd</DestinationName>
    <Purpose>Investment</Purpose>
  </Transaction>
  <Transaction>
    <Date>2023-11-10</Date>
    <Amount>3000</Amount>
    <Currency>EUR</Currency>
    <DestinationAccount>LT12100001110123451</DestinationAccount>
    <DestinationName>Altcoin Global Ltd</DestinationName>
    <Purpose>Investment</Purpose>
  </Transaction>
  <Findings>Unusual transaction pattern; large deposits followed by transfers to offshore account. Subject exhibits signs of being targeted by an investment scam.</Findings>
</SAR>