{
  "case_id": "2024-CX-1047",
  "fraud_type": "Investment Fraud",
  "fraud_subtype": "AI Trading Scam",
  "victim_profile": {
    "age_range": "55-64",
    "income_range": "\u20ac60,000 - \u20ac80,000",
    "country": "Germany",
    "education_level": "Bachelor's Degree"
  },
  "fraudster_profile": {
    "location": "Nigeria",
    "languages_spoken": [
      "English",
      "Pidgin English",
      "Yoruba"
    ]
  },
  "destination_countries": [
    "Marshall Islands",
    "Saint Vincent and the Grenadines"
  ],
  "timeline": [
    {
      "date": "2023-03-15",
      "event": "Victim contacted via Telegram by 'AI Trading Expert'"
    },
    {
      "date": "2023-04-01",
      "event": "Initial deposit made by victim"
    },
    {
      "date": "2023-05-10",
      "event": "Victim receives first 'profit' payout"
    },
    {
      "date": "2023-07-20",
      "event": "Victim attempts to withdraw funds; encounter 'verification' issues"
    },
    {
      "date": "2023-08-15",
      "event": "Victim realizes the scam and reports to authorities"
    },
    {
      "date": "2023-09-01",
      "event": "Initial investigation launched"
    }
  ],
  "assets_involved": [
    {
      "type": "Cryptocurrency (Bitcoin)",
      "amount_range": "\u20ac5,000 - \u20ac10,000"
    },
    {
      "type": "Bank Transfers",
      "amount_range": "\u20ac10,000 - \u20ac15,000"
    }
  ]
}