<?xml version="1.0" encoding="UTF-8"?>
<SAR xmlns:xsi="http://www.w3.org/2001/XMLSchema-instance" xmlns:xsd="http://www.w3.org/2001/XMLSchema">
  <ReportDate>2023-10-17</ReportDate>
  <InstitutionName>Deutsche Bank</InstitutionName>
  <SuspiciousActivity>
    <TransactionDate>2023-09-05</TransactionDate>
    <TransactionAmount currency="EUR">5000</TransactionAmount>
    <TransactionType>Credit</TransactionType>
    <SenderName>Karl Heinz</SenderName>
    <SenderAccount>DExxxxxxxxxxxxx</SenderAccount>
    <RecipientName>NovaTrade AI</RecipientName>
    <RecipientAccount>GBxxxxxxxxxxxxx</RecipientAccount>
    <Description>Deposit to AI Trading Platform</Description>
    <Suspicion>Unusual activity; Potential investment fraud</Suspicion>
  </SuspiciousActivity>
  <Investigator>Anna Schmidt</Investigator>
  <ReportID>DB-20231017-001</ReportID>
</SAR>