{
  "case_id": "2024-03-15-NF-007",
  "fraud_type": "Investment Fraud",
  "fraud_subtype": "AI Trading Scam",
  "victim_profile": {
    "age_range": "55-64",
    "income_range": "$80,000 - $120,000",
    "country": "Canada",
    "education_level": "Bachelor's Degree"
  },
  "fraudster_profile": {
    "location": "Belize",
    "languages_spoken": [
      "English",
      "Spanish"
    ]
  },
  "destination_countries": [
    "Belize",
    "United Arab Emirates",
    "Panama"
  ],
  "timeline": [
    {
      "date": "2023-09-10",
      "event": "Initial contact via LinkedIn"
    },
    {
      "date": "2023-09-28",
      "event": "First investment made"
    },
    {
      "date": "2023-11-15",
      "event": "Victim expresses concerns about performance"
    },
    {
      "date": "2023-12-05",
      "event": "Funds withdrawn from account"
    },
    {
      "date": "2024-01-18",
      "event": "Victim reports fraud"
    }
  ],
  "assets_involved": [
    {
      "type": "Bank Account",
      "amount_range": "$50,000 - $75,000"
    },
    {
      "type": "Cryptocurrency (BTC)",
      "amount_range": "$5,000 - $10,000"
    }
  ]
}