[
  {
    "question": "What was the initial investment amount Dr. Schmidt made to the automated trading platform, according to the first SAR?",
    "answer": "\u20ac5,000"
  },
  {
    "question": "Based on the telegram conversation, what daily return percentage did David Johnson claim Athena AI was generating?",
    "answer": "2.5%"
  },
  {
    "question": "What was the description provided for the initial investment in the first SAR (SAR-2023-10-26-001)?",
    "answer": "Initial investment to automated trading platform."
  },
  {
    "question": "Which entity is identified as the receiver of funds in all three SARs?",
    "answer": "Reliable Trading Solutions Ltd."
  },
  {
    "question": "According to promotional material, what is one key feature of Athena AI?",
    "answer": "100% Automated - No trading experience required."
  },
  {
    "question": "What was the stated reason for the suspicious activity flagged in SAR-2023-11-17-002?",
    "answer": "Victim attempting to withdraw funds denied by platform. Multiple SARs filed regarding similar platform."
  },
  {
    "question": "What did the website screenshot highlight regarding Athena AI's design?",
    "answer": "Creates a sense of sophistication and high-tech innovation, suggesting a trustworthy and profitable investment opportunity."
  },
  {
    "question": "According to the second bank statement, what was the 'Athena AI Profit' amount received on September 22nd?",
    "answer": "+750.00"
  },
  {
    "question": "What action did Dr. Schmidt express in SAR-2023-11-20-003?",
    "answer": "Victim is now expressing concerns about the legitimacy of the platform."
  },
  {
    "question": "What was the total amount invested by Dr. Schmidt as of November 10th, according to the second bank statement?",
    "answer": "\u20ac17,500"
  }
]