<?xml version="1.0" encoding="UTF-8"?>
<SAR>
  <ReportID>INV2024-001</ReportID>
  <ReportingInstitution>First Credit Union</ReportingInstitution>
  <Subject>
    <Name>Eamon O'Connell</Name>
    <Account>IE37RAIB901020292350000000</Account>
  </Subject>
  <Transaction>
    <Date>2023-08-01</Date>
    <Amount>5000</Amount>
    <Currency>EUR</Currency>
    <DestinationAccount>MT1211610401000101010111</DestinationAccount>
    <DestinationName>NovaAurora Investments Ltd</DestinationName>
    <Purpose>Initial Investment</Purpose>
  </Transaction>
</SAR>