<?xml version="1.0" encoding="UTF-8"?>
<SAR>
  <ReportID>INV2024-145</ReportID>
  <ReportingInstitution>Lloyds Bank</ReportingInstitution>
  <Subject>
    <Name>John Smith</Name>
    <Account>0000000000000000001234</Account>
  </Subject>
  <Transaction>
    <Date>2024-01-10</Date>
    <Amount>1000</Amount>
    <Currency>EUR</Currency>
    <DestinationAccount>LT12100001110123451</DestinationAccount>
    <DestinationName>AlgoTradePro Ltd</DestinationName>
    <Purpose>Withdrawal</Purpose>
  </Transaction>
  <Findings>Victim received a small withdrawal, indicating potential 'proof of profit'. Further investigation warranted.</Findings>
</SAR>