[
  {
    "question": "According to the promotional material, what is a key benefit advertised for the AI Trading Pro platform?",
    "answer": "Effortless Profits"
  },
  {
    "question": "What was the initial amount of Helmut Meier's investment, as detailed in the SAR report?",
    "answer": "2500.00 EUR"
  },
  {
    "question": "What reason did David, the investment advisor, initially give for the withdrawal delay?",
    "answer": "A slight technical issue with withdrawals"
  },
  {
    "question": "Based on the provided files, what is the reported win rate of the AI algorithms?",
    "answer": "Over 85%"
  },
  {
    "question": "What type of identification and documentation were requested from Helmut Meier regarding his withdrawal request?",
    "answer": "Copies of his ID and proof of the latest investment transfer"
  },
  {
    "question": "Which country is associated with the receiving account 'MT1234567890', as indicated in the SAR reports?",
    "answer": "MT"
  },
  {
    "question": "What is the total amount Helmut Meier has transferred to AI Trading Pro as of December 4th, 2023?",
    "answer": "-12000.00 EUR"
  },
  {
    "question": "What message was displayed on the trading platform screenshot?",
    "answer": "AI Breaks New Records!"
  },
  {
    "question": "What triggered the Suspicious Activity Report filed on September 5th, 2023?",
    "answer": "Unusual transaction for new account. High-risk investment platform."
  },
  {
    "question": "Considering the emails, promotional material, and chat logs, what is the primary strategy employed by AI Trading Pro to attract and retain investors?",
    "answer": "Promising high returns and effortless profits through AI-powered trading."
  }
]