[
  {
    "question": "What initial investment did David Miller make with AI Wealth Pro?",
    "answer": "AUD $5,000"
  },
  {
    "question": "According to the SAR report, what was the initial assessment of the risk level associated with David Miller's transaction?",
    "answer": "Medium"
  },
  {
    "question": "What activity prompted the Commonwealth Bank of Australia to file a SAR related to David Miller\u2019s account in January 2024?",
    "answer": "An unsuccessful withdrawal request after significant deposits."
  },
  {
    "question": "What was the description provided for the initial transfer of AUD $5,000 to AI Wealth Pro in the bank statement?",
    "answer": "Online Transfer to AI Wealth Pro"
  },
  {
    "question": "What action is David Miller requested to complete, according to email_3.txt?",
    "answer": "Complete a short KYC (Know Your Customer) verification process"
  },
  {
    "question": "Based on the promotional material, what is a key benefit that AI Wealth Pro claims to provide to its investors?",
    "answer": "High-Profit Potential"
  },
  {
    "question": "What is displayed on the platform dashboard, according to the screenshot?",
    "answer": "A graph showing a consistently upward trend labelled 'Portfolio Growth'"
  },
  {
    "question": "What date is associated with David Miller\u2019s most recent transfer of funds to AI Wealth Pro?",
    "answer": "12-07-2024"
  },
  {
    "question": "Based on the SAR report from July 2024, what is David Miller's current reported status concerning AI Wealth Pro?",
    "answer": "Victim reports inability to withdraw funds, potential investment scam"
  },
  {
    "question": "What does promotional material_2.txt offer to potential investors?",
    "answer": "A 50% bonus on their first deposit"
  }
]