<?xml version="1.0" encoding="UTF-8"?>
<SuspiciousActivityReport>
  <ReportDate>2023-11-05</ReportDate>
  <FilerInstitution>Chase Bank</FilerInstitution>
  <AccountName>David Miller</AccountName>
  <AccountID>1234567890</AccountID>
  <TransactionDate>2023-11-01</TransactionDate>
  <TransactionAmount>6.5</TransactionAmount>
  <TransactionCurrency>USD</TransactionCurrency>
  <BeneficiaryName>CryptoKingsRecovery</BeneficiaryName>
  <BeneficiaryAccount>9876543210</BeneficiaryAccount>
  <BeneficiaryCountry>Nigeria</BeneficiaryCountry>
  <SuspicionDescription>Unusual international transfer to an account with vague description. Potential investment scam.</SuspicionDescription>
  <FiledBy>Jane Doe, BSA Analyst</FiledBy>
</SuspiciousActivityReport>