<?xml version="1.0" encoding="UTF-8"?>
<SAR>
  <ReportID>DE2024-123</ReportID>
  <ReportingInstitution>Deutsche Bank</ReportingInstitution>
  <Subject>
    <Name>Victim 1</Name>
    <Account>GR1601101250000000012310695</Account>
  </Subject>
  <Transaction>
    <Date>2023-12-01</Date>
    <Amount>1000</Amount>
    <Currency>EUR</Currency>
    <DestinationAccount>LT12100001110123451</DestinationAccount>
    <DestinationName>Altcoin Global Ltd</DestinationName>
    <Purpose>Investment</Purpose>
  </Transaction>
  <Transaction>
    <Date>2024-02-15</Date>
    <Amount>5000</Amount>
    <Currency>EUR</Currency>
    <DestinationAccount>LT12100001110123451</DestinationAccount>
    <DestinationName>Altcoin Global Ltd</DestinationName>
    <Purpose>Investment</Purpose>
  </Transaction>
  <Findings>Multiple transfers to a company registered in Lithuania with no apparent business activity. Unusual investment pattern for the customer.</Findings>
</SAR>